data_attribute_recommendation_sdk-0.15.2.dist-info/licenses/LICENSE
data_attribute_recommendation_sdk-0.15.2.dist-info/licenses/NOTICE
sap/__init__.py
sap/aibus/__init__.py
sap/aibus/dar/__init__.py
sap/aibus/dar/client/__init__.py
sap/aibus/dar/client/base_client.py
sap/aibus/dar/client/dar_session.py
sap/aibus/dar/client/data_manager_client.py
sap/aibus/dar/client/data_manager_constants.py
sap/aibus/dar/client/exceptions.py
sap/aibus/dar/client/inference_client.py
sap/aibus/dar/client/inference_constants.py
sap/aibus/dar/client/model_manager_client.py
sap/aibus/dar/client/model_manager_constants.py
sap/aibus/dar/client/py.typed
sap/aibus/dar/client/aiapi/__init__.py
sap/aibus/dar/client/aiapi/dar_ai_api_client.py
sap/aibus/dar/client/aiapi/dar_ai_api_file_upload_client.py
sap/aibus/dar/client/util/__init__.py
sap/aibus/dar/client/util/credentials.py
sap/aibus/dar/client/util/http_transport.py
sap/aibus/dar/client/util/lists.py
sap/aibus/dar/client/util/logging.py
sap/aibus/dar/client/util/polling.py
sap/aibus/dar/client/workflow/__init__.py
sap/aibus/dar/client/workflow/model.py
system_tests/__init__.py
system_tests/conftest.py
system_tests/client/__init__.py
system_tests/client/test_data_manager_client.py
system_tests/client/test_model_manager_client.py
system_tests/workflow/__init__.py
system_tests/workflow/test_end_to_end.py
tests/sap/__init__.py
tests/sap/aibus/__init__.py
tests/sap/aibus/dar/__init__.py
tests/sap/aibus/dar/client/__init__.py
tests/sap/aibus/dar/client/test_dar_ai_api_client.py
tests/sap/aibus/dar/client/test_dar_ai_api_file_upload_client.py
tests/sap/aibus/dar/client/test_dar_session.py
tests/sap/aibus/dar/client/test_data_manager_client.py
tests/sap/aibus/dar/client/test_exceptions.py
tests/sap/aibus/dar/client/test_inference_client.py
tests/sap/aibus/dar/client/test_model_manager_client.py
tests/sap/aibus/dar/util/__init__.py
tests/sap/aibus/dar/util/test_credentials.py
tests/sap/aibus/dar/util/test_http_transport.py
tests/sap/aibus/dar/util/test_lists.py
tests/sap/aibus/dar/util/test_logging.py
tests/sap/aibus/dar/util/test_polling.py
data_attribute_recommendation_sdk-0.15.2.dist-info/METADATA
data_attribute_recommendation_sdk-0.15.2.dist-info/WHEEL
data_attribute_recommendation_sdk-0.15.2.dist-info/top_level.txt
data_attribute_recommendation_sdk-0.15.2.dist-info/RECORD
