Metadata-Version: 2.4
Name: data-attribute-recommendation-sdk
Version: 0.15.2
Summary: Data Attribute Recommendation Python SDK
Home-page: https://github.com/sap/data-attribute-recommendation-python-sdk
Author: Michael Haas
Author-email: michael.haas01@sap.com
Project-URL: Documentation, https://data-attribute-recommendation-python-sdk.readthedocs.io/en/latest/
Project-URL: Source, https://github.com/SAP/data-attribute-recommendation-python-sdk
Project-URL: Issue Tracker, https://github.com/SAP/data-attribute-recommendation-python-sdk/issues
Classifier: Development Status :: 5 - Production/Stable
Classifier: Intended Audience :: Developers
Classifier: Intended Audience :: Information Technology
Classifier: Programming Language :: Python :: 3
Classifier: Programming Language :: Python :: 3 :: Only
Classifier: Programming Language :: Python :: 3.6
Classifier: Programming Language :: Python :: 3.7
Classifier: Programming Language :: Python :: 3.8
Classifier: Programming Language :: Python :: 3.9
Classifier: Programming Language :: Python :: 3.10
Classifier: Programming Language :: Python :: Implementation :: CPython
Classifier: Programming Language :: Python :: Implementation :: PyPy
Classifier: Environment :: Console
Classifier: Operating System :: OS Independent
Classifier: Topic :: Scientific/Engineering :: Artificial Intelligence
Classifier: Topic :: Software Development :: Libraries
Classifier: Topic :: Software Development :: Libraries :: Python Modules
Classifier: Typing :: Typed
Classifier: License :: OSI Approved :: Apache Software License
Requires-Python: ~=3.6
License-File: LICENSE
License-File: NOTICE
Requires-Dist: requests~=2.20
Requires-Dist: typing-extensions~=4.0
Requires-Dist: cfenv~=0.5
Requires-Dist: ai-api-client-sdk~=2.4
Requires-Dist: aenum==3.1.12
Dynamic: author
Dynamic: author-email
Dynamic: classifier
Dynamic: description
Dynamic: description-content-type
Dynamic: home-page
Dynamic: license-file
Dynamic: project-url
Dynamic: requires-dist
Dynamic: requires-python
Dynamic: summary
